marche/__init__.py
marche/core.py
marche-0.1.2.dist-info/LICENSE
marche-0.1.2.dist-info/METADATA
marche-0.1.2.dist-info/WHEEL
marche-0.1.2.dist-info/entry_points.txt
marche-0.1.2.dist-info/top_level.txt
marche-0.1.2.dist-info/RECORD
