Metadata-Version: 2.1
Name: marche
Version: 0.1.2
Summary: MaRChE
Home-page: https://github.com/OpenCode/marche
Author: Francesco Apruzzese
Author-email: cescoap@gmail.com
License: GPLv3
Keywords: github massive repository branch git vcs
Platform: UNKNOWN
Classifier: Development Status :: 2 - Pre-Alpha
Classifier: Intended Audience :: Developers
Classifier: License :: OSI Approved :: GNU General Public License v3 (GPLv3)
Classifier: Topic :: Software Development :: Version Control
Classifier: Topic :: Software Development :: Version Control :: Git
Classifier: Topic :: Utilities
Classifier: Programming Language :: Python :: 3.6
Classifier: Programming Language :: Python :: 3.7
Requires-Dist: click (>=7.1.2)
Requires-Dist: pyyaml (>=5.3.1)
Requires-Dist: PyGithub (>=1.53)
